examples/__init__.py
examples/chicago_taxi_pipeline/__init__.py
examples/chicago_taxi_pipeline/pipeline.py
examples/chicago_taxi_pipeline/pipeline_e2e_test.py
examples/usage_guide/__init__.py
examples/usage_guide/custom_component_schema.py
examples/usage_guide/custom_component_schema_e2e_test.py
examples/usage_guide/generate_schema.py
examples/usage_guide/generate_schema_e2e_test.py
examples/usage_guide/model_code.py
examples/usage_guide/simple.py
examples/usage_guide/simple_e2e_test.py
fluent_tfx/__init__.py
fluent_tfx/input_builders.py
fluent_tfx/pipeline_def.py
tests/__init__.py
tests/conftest.py
tests/input_builders_test.py
tests/pipeline_def/__init__.py
tests/pipeline_def/bulk_infer_test.py
tests/pipeline_def/custom_components_test.py
tests/pipeline_def/example_inputs_test.py
tests/pipeline_def/infra_validation_test.py
tests/pipeline_def/input_functions_test.py
tests/pipeline_def/model_evaluation_test.py
tests/pipeline_def/pipeline_def_test.py
tests/pipeline_def/push_test.py
tests/pipeline_def/schema_test.py
tests/pipeline_def/train_test.py
tests/pipeline_def/tune_test.py
fluent_tfx-0.23.1.dist-info/METADATA
fluent_tfx-0.23.1.dist-info/WHEEL
fluent_tfx-0.23.1.dist-info/top_level.txt
fluent_tfx-0.23.1.dist-info/RECORD
