Metadata-Version: 2.1
Name: fluent-tfx
Version: 0.23.1
Summary: A fluent API layer for tensorflow extended e2e machine learning pipelines
Home-page: https://github.com/ntakouris/fluent-tfx
Author: Theodoros Ntakouris
Author-email: zarkopafilis@gmail.com
License: UNKNOWN
Platform: UNKNOWN
Classifier: Development Status :: 4 - Beta
Classifier: Environment :: Console
Classifier: Programming Language :: Python :: 3
Classifier: License :: OSI Approved :: MIT License
Classifier: Operating System :: OS Independent
Requires-Python: >=3.6
